datasimple/__init__.py
datasimple/cli.py
datasimple/core.py
datasimple/period.py
datasimple/sqlite.py
datasimple/xl.py
datasimple-1.0.7.data/scripts/csv-examine
datasimple-1.0.7.data/scripts/csv2importxml
datasimple-1.0.7.data/scripts/csv2xlsx
datasimple-1.0.7.data/scripts/csvfilt
datasimple-1.0.7.data/scripts/get-cpi
datasimple-1.0.7.data/scripts/rpt-export.py
datasimple-1.0.7.data/scripts/sample.py
datasimple-1.0.7.data/scripts/sql2csv
datasimple-1.0.7.data/scripts/sql2importxml
datasimple-1.0.7.data/scripts/sql2xlsx
datasimple-1.0.7.data/scripts/sqlite-comppart
datasimple-1.0.7.data/scripts/sqlite-date
datasimple-1.0.7.data/scripts/template-expand.py
datasimple-1.0.7.data/scripts/xlsx-sheets
datasimple-1.0.7.data/scripts/xlsx2csv
datasimple-1.0.7.data/scripts/xlsx2importxml
datasimple-1.0.7.dist-info/METADATA
datasimple-1.0.7.dist-info/RECORD
datasimple-1.0.7.dist-info/WHEEL
datasimple-1.0.7.dist-info/top_level.txt
