Metadata-Version: 2.1
Name: datasimple
Version: 1.0.7
Summary: Utility library and scripts for simpler data-processing tasks
Home-page: https://github.com/CraigKelly/datasimple
Author: Craig Kelly
Author-email: craig.n.kelly@gmail.com
License: Apache Version 2.0
Keywords: analytics data
Platform: UNKNOWN
Classifier: Development Status :: 4 - Beta
Classifier: Intended Audience :: Developers
Classifier: Programming Language :: Python :: 3
Requires-Python: >=3.4
Requires-Dist: colorclass (>=2.2.0)
Requires-Dist: openpyxl (>=2.5.7)
Requires-Dist: lxml (>=4.2.5)
Requires-Dist: requests (>=2.19.1)
Requires-Dist: terminaltables (>=3.1.0)
